matpak/__init__.py
matpak/errors.py
matpak/io.py
matpak/mat.py
matpak/types.py
matpak/vec.py
matpak-1.0.1.dist-info/licenses/LICENSE
matpak-1.0.1.dist-info/METADATA
matpak-1.0.1.dist-info/WHEEL
matpak-1.0.1.dist-info/top_level.txt
matpak-1.0.1.dist-info/RECORD
