Metadata-Version: 2.4
Name: matpak
Version: 1.0.1
Summary: Matrix Utilization Python Package
Author-email: Sajjad Anghooty <anghootys@gmail.com>
License-Expression: MIT
Project-URL: Homepage, https://github.com/anghootys/matpak
Project-URL: Issues, https://github.com/anghootys/matpak/issues
Classifier: Programming Language :: Python :: 3
Classifier: Operating System :: OS Independent
Requires-Python: >=3.9
License-File: LICENSE
Dynamic: license-file
